LICENSE
README.md
setup.py
apicutils/__init__.py
apicutils/basic_io.py
apicutils/composition.py
apicutils/dataframes.py
apicutils/matrix_inversion.py
apicutils/num_der.py
apicutils/parallel.py
apicutils/prints.py
apicutils/raise_warn_call.py
apicutils/safe_call.py
apicutils/sets.py
apicutils/shape.py
apicutils/timed_run.py
apicutils/vectorize.py
apicutils.egg-info/PKG-INFO
apicutils.egg-info/SOURCES.txt
apicutils.egg-info/dependency_links.txt
apicutils.egg-info/requires.txt
apicutils.egg-info/top_level.txt